lazyval/__init__.py
lazyval-0.1.0.dist-info/METADATA
lazyval-0.1.0.dist-info/WHEEL
lazyval-0.1.0.dist-info/licenses/LICENSE
lazyval-0.1.0.dist-info/RECORD
