Metadata-Version: 2.4
Name: lazyval
Version: 0.1.0
Summary: A lazy evaluation wrapper for Python with JSON/YAML serialization support
Project-URL: Homepage, https://github.com/tintty1/lazyval
Project-URL: Repository, https://github.com/tintty1/lazyval
License: MIT
License-File: LICENSE
Keywords: deferred,evaluation,json,lazy,proxy,yaml
Classifier: Development Status :: 4 - Beta
Classifier: Intended Audience :: Developers
Classifier: License :: OSI Approved :: MIT License
Classifier: Operating System :: OS Independent
Classifier: Programming Language :: Python :: 3
Classifier: Programming Language :: Python :: 3.10
Classifier: Programming Language :: Python :: 3.11
Classifier: Programming Language :: Python :: 3.12
Classifier: Programming Language :: Python :: 3.13
Classifier: Topic :: Software Development :: Libraries :: Python Modules
Classifier: Typing :: Typed
Requires-Python: >=3.10
Provides-Extra: jinja
Requires-Dist: jinja2>=3.0; extra == 'jinja'
Provides-Extra: yaml
Requires-Dist: pyyaml>=6.0; extra == 'yaml'
